README.rst
setup.py
fabric_shuttle.egg-info/PKG-INFO
fabric_shuttle.egg-info/SOURCES.txt
fabric_shuttle.egg-info/dependency_links.txt
fabric_shuttle.egg-info/requires.txt
fabric_shuttle.egg-info/top_level.txt
shuttle/__init__.py
shuttle/deploy.py
shuttle/formats.py
shuttle/shared.py
shuttle/x.py
shuttle/hooks/__init__.py
shuttle/hooks/decorators.py
shuttle/hooks/defaults.py
shuttle/services/__init__.py
shuttle/services/collectd.py
shuttle/services/cron.py
shuttle/services/geoip.py
shuttle/services/memcached.py
shuttle/services/mysql.py
shuttle/services/nginx.py
shuttle/services/postgis.py
shuttle/services/postgres.py
shuttle/services/redis.py
shuttle/services/s3.py
shuttle/services/service.py
shuttle/services/snowplow.py
shuttle/services/supervisor.py
shuttle/services/uwsgi.py
shuttle/templates/manage.py
shuttle/templates/nginx-site-https.conf
shuttle/templates/nginx-site.conf
shuttle/templates/s3-ajax.js
shuttle/templates/supervisor-systemd.conf
shuttle/templates/supervisor-upstart.conf
shuttle/templates/uwsgi-app.ini