Metadata-Version: 1.1
Name: fabric-shuttle
Version: 0.0.22
Summary: Declarative service-oriented approach with hooks for using Fabric to provision a machine or vagrant box.
Home-page: https://github.com/mvx24/fabric-shuttle
Author: mvx24
Author-email: cram2400@gmail.com
License: MIT
Keywords: fabric deployment development vagrant provisioning services
Platform: UNKNOWN
Classifier: Development Status :: 4 - Beta
Classifier: Environment :: Console
Classifier: Framework :: Django
Classifier: License :: OSI Approved :: MIT License
Classifier: Operating System :: MacOS :: MacOS X
Classifier: Operating System :: POSIX
Classifier: Operating System :: Unix
Classifier: Programming Language :: Python :: 2.7
Classifier: Programming Language :: Python :: 2 :: Only
Classifier: Topic :: System :: Installation/Setup
Classifier: Topic :: System :: Software Distribution
Classifier: Topic :: System :: Systems Administration
